maraboupy/MarabouUtils.py
maraboupy/MarabouMain.py
maraboupy/Marabou.py
maraboupy/MarabouNetworkTF.py
maraboupy/__init__.py
maraboupy/MarabouNetworkNNet.py
maraboupy/MarabouNetworkONNX.py
maraboupy/MarabouCore.cpython-38-x86_64-linux-gnu.so
maraboupy/MarabouNetwork.py
maraboupy/__main__.py
maraboupy/MarabouCore.cpp
maraboupy/MarabouPythonic.py
maraboupy/parsers/ONNXParser.py
maraboupy/parsers/InputQueryBuilder.py
maraboupy-2.0.0.dist-info/top_level.txt
maraboupy-2.0.0.dist-info/AUTHORS
maraboupy-2.0.0.dist-info/METADATA
maraboupy-2.0.0.dist-info/WHEEL
maraboupy-2.0.0.dist-info/entry_points.txt
maraboupy-2.0.0.dist-info/RECORD
maraboupy-2.0.0.dist-info/COPYING
