Metadata-Version: 2.1
Name: maraboupy
Version: 2.0.0
Summary: A package wrapping the Marabou Neural Network Verification tool.
Author: The Marabou Development Team
License: Marabou is copyright (C) 2017-2019 by its
Requires-Python: <=3.12,>=3.8
License-File: COPYING
License-File: AUTHORS
Provides-Extra: test
Requires-Dist: numpy <2,>=1.21.0 ; extra == 'test'
Requires-Dist: onnx <2,>=1.15.0 ; extra == 'test'
Requires-Dist: onnxruntime <2,>=1.12.0 ; extra == 'test'
Requires-Dist: pytest <8,>=7.2.1 ; extra == 'test'
Requires-Dist: pytest-cov <5,>=4.0.0 ; extra == 'test'
Requires-Dist: tensorflow <2.13,>=2.10 ; extra == 'test'
